figcow/__init__.py
figcow/__main__.py
figcow/process.py
figcow-1.0.3.dist-info/LICENSE
figcow-1.0.3.dist-info/METADATA
figcow-1.0.3.dist-info/WHEEL
figcow-1.0.3.dist-info/entry_points.txt
figcow-1.0.3.dist-info/top_level.txt
figcow-1.0.3.dist-info/RECORD
