Metadata-Version: 2.1
Name: figcow
Version: 1.0.3
Summary: Python cowsay that looks like a figlet
Home-page: https://github.com/donno2048/figcow
Author: Elisha Hollander
License: MIT
Platform: UNKNOWN
Classifier: Programming Language :: Python :: 3
License-File: LICENSE
